clienttracker/__init__.py
clienttracker/admin.py
clienttracker/apps.py
clienttracker/models.py
clienttracker/tests.py
clienttracker/urls.py
clienttracker/views.py
clienttracker/static/js/tracer.js
django_client_tracker-0.0.2.dist-info/DESCRIPTION.rst
django_client_tracker-0.0.2.dist-info/METADATA
django_client_tracker-0.0.2.dist-info/RECORD
django_client_tracker-0.0.2.dist-info/WHEEL
django_client_tracker-0.0.2.dist-info/metadata.json
django_client_tracker-0.0.2.dist-info/top_level.txt
